{
  "cate": "2",
  "date": "12æ27æ¥ 17æ45å",
  "datetime": "2018-12-27T17:45",
  "video": "/news/html/20181227/movie/k10011761601_201812271736_201812271737.html",
  "duration": 35,
  "img": "html/20181227/K10011761601_1812271736_1812271745_01_03.jpg",
  "title": "ことしもあとわずか 京都で除夜の鐘の「試しづき」",
  "summary": "大みそかを前に、京都の知恩院では重さがおよそ70トンもある釣り鐘で除夜の鐘の「試しづき」が行われました。",
  "more": "知恩院では毎年、大みそかに江戸時代から伝わる重さおよそ70トンの巨大な釣り鐘をついて新年を迎えています。27日は本番さながらに鐘をつく「試しづき」が行われました。<br /><br />鐘に打ちつける「しゅもく」と呼ばれる棒は長さが４メートル以上、重さは350キロもあります。<br />僧侶たちは「しゅもく」から伸びる17本の綱を一人一人しっかり握り、掛け声とともにあおむけに倒れ込むような姿勢になりながら、全身で鐘をついていきました。<br />辺りには荘厳な音が響き渡り、訪れた人たちが歓声を上げていました。<br /><br />ことし初めて鐘をつく僧侶の大西浄彦さん（24）は「毎年、知恩院の除夜の鐘を楽しみにしている人がいるので、しっかりと息を合わせてつきたいです」と話していました。<br />また、神奈川県から訪れた28歳の男性は「体に響く大きな音で、迫力がありました。ことしは災害が多かったので、来年はいい年になってほしいです」と話していました。<br /><br />知恩院の除夜の鐘は大みそかの午後10時40分ごろから108回つかれるということです。",
  "body": [
    {
      "title": "",
      "img": "",
      "align": "",
      "text": "",
      "textPos": ""
    }
  ],
  "relationNews": [
    {
      "link": "html/20181227/k10011761221000.html",
      "title": "恒例のえとの引き継ぎ式 大阪 通天閣",
      "date": "12月27日  12時18分",
      "datetime": "2018-12-27T12:18",
      "imgPath": "html/20181227/K10011761221_1812271204_1812271218_01_02.jpg",
      "iconPath": "html/20181227/K10011761221_1812271204_1812271218_02_01.jpg",
      "video": "https://www3.nhk.or.jp/news/html/20181227/movie/k10011761221_201812271705_201812271708.html",
      "duration": 27
    },
    {
      "link": "html/20181226/k10011760571000.html",
      "title": "孫へのお年玉 平均7700円 「東高西低」",
      "date": "12月26日  18時20分",
      "datetime": "2018-12-26T18:20",
      "imgPath": "html/20181226/K10011760571_1812262026_1812262027_01_02.jpg",
      "iconPath": "html/20181226/K10011760571_1812262026_1812262027_02_01.jpg",
      "video": "https://www3.nhk.or.jp/news/html/20181226/movie/k10011760571_201812262130_201812262134.html",
      "duration": 18
    },
    {
      "link": "html/20181225/k10011759511000.html",
      "title": "「今年限りで失礼します」",
      "date": "12月25日  20時05分",
      "datetime": "2018-12-25T20:05",
      "imgPath": "html/20181225/K10011759511_1812251834_1812251853_01_02.jpg",
      "iconPath": "html/20181225/K10011759511_1812251834_1812251853_02_01.jpg",
      "video": "",
      "duration": 0
    }
  ],
  "relationLink": [
    {
      "link": "http://www3.nhk.or.jp/lnews/kyoto/",
      "title": "NHK京都放送局",
      "time": "各地のニュース",
      "datetime": ""
    }
  ],
  "word": [],
  "news_id": "k10011761601000",
  "yyyy": "2018",
  "mm": "12",
  "dd": "27",
  "url": "https://www3.nhk.or.jp/news/html/20181227/k10011761601000.html"
}