{
  "news_id": "k10011757131000",
  "news_prearranged_time": "2018-12-26 18:15:00",
  "title": "そばの実ができなくて店のそばの値段が上がるかもしれない",
  "title_with_ruby": "そばの<ruby>実<rt>み</rt></ruby>ができなくて<ruby>店<rt>みせ</rt></ruby>のそばの<ruby>値段<rt>ねだん</rt></ruby>が<ruby>上<rt>あ</rt></ruby>がるかもしれない",
  "outline_with_ruby": "<p><ruby>日本<rt>にっぽん</rt></ruby>では１２<ruby>月<rt>がつ</rt></ruby>３１<ruby>日<rt>にち</rt></ruby>に、<ruby>長<rt>なが</rt></ruby>く<ruby>生<rt>い</rt></ruby>きることを<a href='javascript:void(0)' class='dicWin' id='id-0002'><ruby>願<rt>ねが</rt></ruby>っ</a>て<a href='javascript:void(0)' class='dicWin' id='id-0000'>そば</a>を<ruby>食<rt>た</rt></ruby>べる<ruby>人<rt>ひと</rt></ruby>が<ruby>大勢<rt>おおぜい</rt></ruby>います。",
  "has_news_web_image": false,
  "has_news_web_movie": false,
  "has_news_easy_image": true,
  "has_news_easy_movie": false,
  "has_news_easy_voice": true,
  "news_web_image_uri": "",
  "news_web_movie_uri": "",
  "news_easy_image_uri": "k10011757131000.jpg",
  "news_easy_movie_uri": "''",
  "news_easy_voice_uri": "k10011757131000.mp4",
  "url": "http://www3.nhk.or.jp/news/easy/k10011757131000/k10011757131000.html"
}